snappay/__init__.py
snappay/client.py
snappay/config.py
snappay/constants.py
snappay/logger.py
snappay/sse_types.py
snappay/types.py
snappay/utils.py
snappay/services/__init__.py
snappay/services/access.py
snappay/services/base.py
snappay/services/checkout.py
snappay/services/customers.py
snappay/services/sse.py
snappay/services/usage.py
snappay-0.0.1b0.dist-info/licenses/LICENSE
snappay-0.0.1b0.dist-info/METADATA
snappay-0.0.1b0.dist-info/WHEEL
snappay-0.0.1b0.dist-info/top_level.txt
snappay-0.0.1b0.dist-info/RECORD
